{
	//用户正在浏览的文章
	"lookActives":[
		"图森推自动驾驶卡车工信部部长现场试乘2",
		"图森推自动驾驶卡车工信部部长现场试乘3",
		"图森推自动驾驶卡车工信部部长现场试乘1",
		"图森推自动驾驶卡车工信部部长现场试乘3",
		"图森推自动驾驶卡车工信部部长现场试乘1",
		"图森推自动驾驶卡车工信部部长现场试乘2",
		"图森推自动驾驶卡车工信部部长现场试乘3",
	],
	//车系大类的比例
	"proportion":[
		{
			"name":["载货车","牵引车","自卸车","其他"],
			"number":[45.54,23.32,32.23,20.54]
		},
		{
			"name":["载货车","牵引车","自卸车"],
			"number":[45.54,23.32,32.23,20.54]
		},
		{
			"name":["新用户","回访用户",],
			"number":[60,40]
		}
	],
	//服务卡友的基数
	"number":1312017627,
	//当前正在询价的地区信息
	"footerPrice":{
		"cityName":["海门"],
		"coordinate":[121.15, 31.89],
		"phone":"9390",
		"title":"解放J69领航版自卸车"
	},
	//用户行为
	"userActives":{
		"name":["用户行为","用户发帖","用户点赞"],
		"content":[
			[
				{
					"name":"蛤蟆哥",
					"action":"发表了个帖子",
					"title":"戴眼镜是中怎样体验"
				},
				{
					"name":"哈哈哈",
					"action":"关注了",
					"title":"蛤蟆哥"
				},
			],
			[],
			[]
		]
	},
	//互动达人
	"userRank":[
		[
			{
				"name":"哈哈哈",
				"src":"头像图片地址",
			},
			{},
			{}
		],[],[]
	],
	//每小时热门排行榜 || 视频排行榜 || 文章排行榜
	"rankVideos":{
		"name":["每小时转发热门排行榜","每小时热门转发的视频前5","每天热门转发的文章前5"],
		"content":[
			[
				"骑手搭卡车“顺风车”，惨遭碾压断10根肋骨",
				"实拍二师兄冒死跳车，300斤肉直接往地上摔",
				"司机太拼了，轮胎报废了也要上坡，就是不信",
				"交警快来，快来呀！这小子挑衅你们"
			],[],[]
		]
	}
}